PyOSGPUP/__init__.py
PyOSGPUP/segypy.py
PyOSGPUP/signalpy.py
PyOSGPUP/synthe_seismo.py
PyOSGPUP/tuning_wedge_acces.py
PyOSGPUP/wavelet.py
PyOSGPUP-1.0.3.dist-info/DESCRIPTION.rst
PyOSGPUP-1.0.3.dist-info/METADATA
PyOSGPUP-1.0.3.dist-info/RECORD
PyOSGPUP-1.0.3.dist-info/WHEEL
PyOSGPUP-1.0.3.dist-info/metadata.json
PyOSGPUP-1.0.3.dist-info/top_level.txt
sample/__init__.py
sample/package_data.dat
