Metadata-Version: 2.0
Name: PyOSGPUP
Version: 1.0.3
Summary: An open-source library for geophysical data processing, modeling, and interpretation based on Python.
Home-page: https://sites.google.com/site/metkomup/
Author: Komputasi Geofisika - Universitas Pertamina
Author-email: metkom.up@gmail.com
License: UNKNOWN
Project-URL: Bug Reports, https://github.com/Metkom/PyOSGPUP/issues
Project-URL: Say Thanks!, https://sites.google.com/site/metkomup/pyosgpup
Project-URL: Source, https://github.com/Metkom/PyOSGPUP
Keywords: geophysical data processing,modeling,and interpretation
Platform: Windows
Platform: Linux
Platform: Mac OS-X
Classifier: Development Status :: 3 - Alpha
Classifier: Intended Audience :: Developers
Classifier: Topic :: Software Development :: Build Tools
Classifier: License :: OSI Approved :: MIT License
Classifier: Programming Language :: Python :: 3.4
Classifier: Programming Language :: Python :: 3.5
Classifier: Programming Language :: Python :: 3.6
Requires-Dist: numpy
Requires-Dist: matplotlib
